pycrusher/__init__.py
pycrusher/__main__.py
pycrusher/cli.py
pycrusher/core.py
pycrusher-0.3.11.dist-info/LICENSE
pycrusher-0.3.11.dist-info/METADATA
pycrusher-0.3.11.dist-info/WHEEL
pycrusher-0.3.11.dist-info/entry_points.txt
pycrusher-0.3.11.dist-info/top_level.txt
pycrusher-0.3.11.dist-info/RECORD
