Metadata-Version: 2.1
Name: pycrusher
Version: 0.3.11
Summary: Generate lossy JPEG compressions for fun!
Author-email: Jones Martins <15959626+jonesmartins@users.noreply.github.com>
License: Apache 2.0
Project-URL: Issues, https://github.com/jonesmartins/pycrusher/issues
Project-URL: Repository, https://github.com/jonesmartins/pycrusher
Keywords: image processing,jpeg,lossy compression
Classifier: Development Status :: 4 - Beta
Classifier: Environment :: Console
Classifier: Intended Audience :: End Users/Desktop
Classifier: License :: OSI Approved :: Apache Software License
Classifier: Operating System :: OS Independent
Classifier: Programming Language :: Python :: 3 :: Only
Classifier: Programming Language :: Python :: 3.7
Classifier: Programming Language :: Python :: 3.8
Classifier: Programming Language :: Python :: 3.9
Classifier: Programming Language :: Python :: 3.10
Classifier: Programming Language :: Python :: 3.11
Classifier: Programming Language :: Python :: 3.12
Classifier: Programming Language :: Python :: 3.13
Classifier: Topic :: Artistic Software
Classifier: Typing :: Typed
Requires-Python: >=3.7
License-File: LICENSE
Requires-Dist: importlib-metadata >=6.7
Requires-Dist: pillow >=9.5
Requires-Dist: tqdm >=4.66.5
